{
  "diagnosis": "/Disease/Disorder/Injury 2 OB/GYN HISTORY: Menopausal Status Date of First Menses 18 Pye-menopausal pean od Menopausal Date of Last Menses 1 Post-menopausal spear rob",
  "microscopic": "",
  "margins": "",
  "lymph_nodes": "",
  "ptnm": "",
  "keywords": [
    "positive",
    "negative"
  ],
  "full": "Mp-0-3 bu Caneca rma, wiplinaiey hated wes 8500/3 Site ie te beast, Upper outer gusdient 650.4 CQee brut! wed ea 4 a i mone vir inical Case Report (For Collection of Cancerous Tissue) = (OH 30263 a I personally informed this patient that a snecimen s) would be collected to be used for research purposes. I reviewed the FORM with the patient and answered any questions the patient had. The patient then signed the consent form as a free and voluntary act. A copy of this informed consent document will be retained at our institution. Name of Physician or Study Coordinator Signature QQ Pigetar ers a ie A al Single i Divorced 0 Widow ee FS RTS TORV OR PRESENT. ILLNESS*: Chief Complaints: Tn ty Me mya breect Symptoms: Sr chur the Aight te Performance Scale (Karnofsky Score): 0 60-70 Symptomatic, in bed less than 50% of day 5 ache i ern te naar Sinus nn PAST MEDICAL HISTORY. Diagnosis/Disease/Disorder/Injury 2 OB/GYN HISTORY: Menopausal Status Date of First Menses 18 Pye-menopausal pean od Menopausal Date of Last Menses 1 Post-menopausal spear rob Birth Control: Condom CG Oral Contraceptive b IUD Fast parson Result 1 Positive: 1 Positive: DNegative Positive: 2 res a Negative Positive, : Negative Positive__ . ve Positive: BIT Gell Markers: DIAGNOSTIC STUDIES Results 7 Bovecat Collected by: _ Preserved by: Pathology Form # Examined Pathological Staging No Mo Stage: CONSOLIDATED DIAGNOSTIC Mieroscopie Appearance: PATHOLOGY FoRM* (Neciear Grade, (Comme,",
  "case_id": "TCGA-C8-A1HJ"
}